<Properties StartupConfiguration="{BCB3E3EB-E953-C502-0FAB-AAA076AEC0FE}|">
  <MonoDevelop.Ide.Workbench ActiveDocument="Assets/Scripts/DefenderSpawner.cs">
    <Files>
      <File FileName="Assets/Scripts/Shooter.cs" Line="44" Column="6" />
      <File FileName="Assets/Scripts/Attacker.cs" Line="11" Column="19" />
      <File FileName="Assets/Scripts/Health.cs" Line="1" Column="1" />
      <File FileName="Assets/Scripts/Defender.cs" Line="1" Column="1" />
      <File FileName="Assets/Scripts/Lizard.cs" Line="14" Column="2" />
      <File FileName="Assets/Scripts/Projectile.cs" Line="1" Column="1" />
      <File FileName="Assets/Scripts/AttackerSpawner.cs" Line="1" Column="1" />
      <File FileName="Assets/Scripts/DefenderSpawner.cs" Line="1" Column="1" />
    </Files>
  </MonoDevelop.Ide.Workbench>
  <MonoDevelop.Ide.DebuggingService.PinnedWatches />
  <MonoDevelop.Ide.Workspace ActiveConfiguration="Debug" />
  <MonoDevelop.Ide.ItemProperties.Assembly-CSharp PreferredExecutionTarget="3ec1f0a5-9b55-4b39-8b0e-5a25312391ed" />
  <MonoDevelop.Ide.DebuggingService.Breakpoints>
    <BreakpointStore />
  </MonoDevelop.Ide.DebuggingService.Breakpoints>
  <MultiItemStartupConfigurations />
</Properties>